weblite_framework/database/models.py
weblite_framework/exceptions/__init__.py
weblite_framework/exceptions/auth.py
weblite_framework/exceptions/base.py
weblite_framework/exceptions/repository.py
weblite_framework/exceptions/service.py
weblite_framework/logging/__init__.py
weblite_framework/logging/formatters.py
weblite_framework/logging/logger.py
weblite_framework/provider/__init__.py
weblite_framework/provider/s3.py
weblite_framework/repository/__init__.py
weblite_framework/repository/base.py
weblite_framework/repository/common.py
weblite_framework/schemas/__init__.py
weblite_framework/schemas/base.py
weblite_framework/schemas/validators.py
weblite_framework/services/__init__.py
weblite_framework/services/base.py
weblite_framework/services/health.py
weblite_framework/settings/__init__.py
weblite_framework/settings/s3.py
weblite_framework-0.4.2.dist-info/METADATA
weblite_framework-0.4.2.dist-info/WHEEL
weblite_framework-0.4.2.dist-info/RECORD
