Metadata-Version: 2.3
Name: weblite_framework
Version: 0.4.2
Summary: 
Author: Чернов Михаил
Author-email: mihail.tchernov@yandex.ru
Requires-Python: ==3.12.6
Classifier: Programming Language :: Python :: 3
Requires-Dist: aioboto3 (==15.1.0)
Requires-Dist: pydantic-settings (==2.10.1)
Requires-Dist: pydantic[email] (==2.11.7)
Requires-Dist: sqlalchemy[asyncio] (==2.0.36)
